mlup/__init__.py
mlup/baseline.py
mlup/config.py
mlup/constants.py
mlup/errors.py
mlup/up.py
mlup/console_scripts/__init__.py
mlup/console_scripts/command.py
mlup/console_scripts/make_app.py
mlup/console_scripts/run.py
mlup/console_scripts/utils.py
mlup/console_scripts/validate_config.py
mlup/ml/__init__.py
mlup/ml/empty.py
mlup/ml/model.py
mlup/ml/binarization/__init__.py
mlup/ml/binarization/base.py
mlup/ml/binarization/joblib.py
mlup/ml/binarization/lightgbm.py
mlup/ml/binarization/memory.py
mlup/ml/binarization/onnx.py
mlup/ml/binarization/pickle.py
mlup/ml/binarization/tensorflow.py
mlup/ml/binarization/torch.py
mlup/ml/data_transformers/__init__.py
mlup/ml/data_transformers/base.py
mlup/ml/data_transformers/numpy_data_transformer.py
mlup/ml/data_transformers/pandas_data_transformer.py
mlup/ml/data_transformers/src_data_transformer.py
mlup/ml/data_transformers/tf_tensor_data_transformer.py
mlup/ml/data_transformers/torch_tensor_data_transformer.py
mlup/ml/storage/__init__.py
mlup/ml/storage/base.py
mlup/ml/storage/local_disk.py
mlup/ml/storage/memory.py
mlup/utils/__init__.py
mlup/utils/collections.py
mlup/utils/crypto.py
mlup/utils/interspection.py
mlup/utils/logging.py
mlup/utils/loop.py
mlup/utils/oop.py
mlup/utils/profiling.py
mlup/web/__init__.py
mlup/web/api_docs.py
mlup/web/api_errors.py
mlup/web/api_validators.py
mlup/web/app.py
mlup/web/architecture/__init__.py
mlup/web/architecture/base.py
mlup/web/architecture/batching.py
mlup/web/architecture/directly_to_predict.py
mlup/web/architecture/worker_and_queue.py
pymlup-0.2.3.dist-info/LICENCE
pymlup-0.2.3.dist-info/METADATA
pymlup-0.2.3.dist-info/WHEEL
pymlup-0.2.3.dist-info/entry_points.txt
pymlup-0.2.3.dist-info/top_level.txt
pymlup-0.2.3.dist-info/RECORD
