Metadata-Version: 2.1
Name: pymlup
Version: 0.2.3
Summary: MLup framework, fast ml to production, easy to learn, easy to use.
Author-email: Deys Timofey <nxexox@gmail.com>
Project-URL: Homepage, https://github.com/nxexox/pymlup
Project-URL: Documentation, https://github.com/nxexox/pymlup/docs
Project-URL: Repository, https://github.com/nxexox/pymlup
Classifier: Intended Audience :: Information Technology
Classifier: Intended Audience :: Developers
Classifier: Intended Audience :: Science/Research
Classifier: Intended Audience :: System Administrators
Classifier: Operating System :: OS Independent
Classifier: Programming Language :: Python :: 3
Classifier: Programming Language :: Python
Classifier: Topic :: Internet
Classifier: Topic :: Software Development :: Code Generators
Classifier: Topic :: Software Development :: Libraries :: Application Frameworks
Classifier: Topic :: Software Development :: Libraries :: Python Modules
Classifier: Topic :: Software Development :: Libraries
Classifier: Topic :: Software Development
Classifier: Development Status :: 4 - Beta
Classifier: Environment :: Web Environment
Classifier: Framework :: AsyncIO
Classifier: Framework :: FastAPI
Classifier: Framework :: Pydantic
Classifier: Framework :: Pydantic :: 1
Classifier: License :: OSI Approved :: MIT License
Classifier: Programming Language :: Python :: 3 :: Only
Classifier: Programming Language :: Python :: 3.7
Classifier: Programming Language :: Python :: 3.8
Classifier: Programming Language :: Python :: 3.9
Classifier: Programming Language :: Python :: 3.10
Classifier: Programming Language :: Python :: 3.11
Classifier: Topic :: Internet :: WWW/HTTP :: HTTP Servers
Classifier: Topic :: Internet :: WWW/HTTP
Requires-Python: >=3.7
License-File: LICENCE
Requires-Dist: fastapi[all] <0.100.0,>=0.95.2
Requires-Dist: pyyaml <7.0.0,>=6.0.0
Requires-Dist: numpy <2.0.0,>=1.0.0
Provides-Extra: lightgbm
Requires-Dist: lightgbm <5.0.0,>=4.0.0 ; extra == 'lightgbm'
Provides-Extra: onnx
Requires-Dist: onnx <2.0.0,>=1.0.0 ; extra == 'onnx'
Requires-Dist: onnxruntime <1.16 ; extra == 'onnx'
Provides-Extra: scikit-learn
Requires-Dist: scikit-learn ; (python_version < "3.8") and extra == 'scikit-learn'
Requires-Dist: scikit-learn <1.3.0,>=1.2.0 ; (python_version >= "3.8") and extra == 'scikit-learn'
Provides-Extra: tensorflow
Requires-Dist: tensorflow <3.0.0,>=2.0.0 ; extra == 'tensorflow'
Provides-Extra: tests
Requires-Dist: pytest <8.0.0,>=7.0.0 ; extra == 'tests'
Requires-Dist: pytest-asyncio ==0.21.0 ; extra == 'tests'
Requires-Dist: joblib <1.3.0,>=1.2.0 ; extra == 'tests'
Requires-Dist: lightgbm <5.0.0,>=4.0.0 ; extra == 'tests'
Requires-Dist: onnx <2.0.0,>=1.0.0 ; extra == 'tests'
Requires-Dist: onnxruntime <1.16 ; extra == 'tests'
Requires-Dist: tf2onnx <2.0.0,>=1.0.0 ; extra == 'tests'
Requires-Dist: skl2onnx <2.0.0,>=1.0.0 ; extra == 'tests'
Requires-Dist: pandas ; (python_version < "3.8") and extra == 'tests'
Requires-Dist: scikit-learn ; (python_version < "3.8") and extra == 'tests'
Requires-Dist: tensorflow ; (python_version < "3.8") and extra == 'tests'
Requires-Dist: torch ; (python_version < "3.8") and extra == 'tests'
Requires-Dist: nbclient ==0.7.4 ; (python_version < "3.8") and extra == 'tests'
Requires-Dist: jupyterlab-pygments ==0.2.2 ; (python_version < "3.8") and extra == 'tests'
Requires-Dist: pandas <3.0.0,>=2.0.0 ; (python_version >= "3.8") and extra == 'tests'
Requires-Dist: scikit-learn <1.3.0,>=1.2.0 ; (python_version >= "3.8") and extra == 'tests'
Requires-Dist: tensorflow ==2.13.1 ; (python_version >= "3.8") and extra == 'tests'
Requires-Dist: torch <3.0.0,>=2.0.0 ; (python_version >= "3.8") and extra == 'tests'
Requires-Dist: nbclient ==0.10.0 ; (python_version >= "3.8") and extra == 'tests'
Requires-Dist: jupyterlab-pygments ==0.3.0 ; (python_version >= "3.8") and extra == 'tests'
Provides-Extra: torch
Requires-Dist: torch ; (python_version < "3.8") and extra == 'torch'
Requires-Dist: torch <3.0.0,>=2.0.0 ; (python_version >= "3.8") and extra == 'torch'
